MANIFEST.in
setup.py
taskwarrior_timesheets/__init__.py
taskwarrior_timesheets/messages.py
taskwarrior_timesheets/taskwarrior_timesheets
taskwarrior_timesheets/utils.py
taskwarrior_timesheets.egg-info/PKG-INFO
taskwarrior_timesheets.egg-info/SOURCES.txt
taskwarrior_timesheets.egg-info/dependency_links.txt
taskwarrior_timesheets.egg-info/entry_points.txt
taskwarrior_timesheets.egg-info/requires.txt
taskwarrior_timesheets.egg-info/top_level.txt