Metadata-Version: 1.0
Name: taskwarrior-timesheets
Version: 0.1.2
Summary: Time tracking for Task Warrior, connects to the Tempo Timesheets plugin in JIRA
Home-page: http://git@stash.t.is:7999/san/taskwarrior-timesheets.git
Author: Eric Nielsen
Author-email: ericn@tmsoftware.is
License: UNKNOWN
Platform: UNKNOWN
